fkin_anfu/__init__.py
fkin_anfu/cli/__init__.py
fkin_anfu/cli/main.py
fkin_anfu/cli/parse_cmd.py
fkin_anfu/common/__init__.py
fkin_anfu/common/constants.py
fkin_anfu/common/enums.py
fkin_anfu/core/__init__.py
fkin_anfu/models/__init__.py
fkin_anfu/parsers/__init__.py
fkin_anfu/parsers/afrog_parser.py
fkin_anfu/parsers/base_parser.py
fkin_anfu/parsers/fscan_parser.py
fkin_anfu/parsers/parse_manager.py
fkin_anfu/parsers/models/finding_result.py
fkin_anfu/utils/__init__.py
fkin_anfu/utils/cli_utils.py
fkin_anfu/utils/color_utils.py
fkin_anfu/utils/common_utils.py
fkin_anfu/utils/datetime_utils.py
fkin_anfu/utils/db_utils.py
fkin_anfu/utils/env_utils.py
fkin_anfu/utils/excel_utils.py
fkin_anfu/utils/file_utils.py
fkin_anfu/utils/ip_utils.py
fkin_anfu/utils/log_utils.py
fkin_anfu/utils/output_utils.py
fkin_anfu/utils/path_utils.py
fkin_anfu/utils/string_utils.py
fkin_anfu-0.5.2.dist-info/licenses/LICENSE
fkin_anfu-0.5.2.dist-info/METADATA
fkin_anfu-0.5.2.dist-info/WHEEL
fkin_anfu-0.5.2.dist-info/entry_points.txt
fkin_anfu-0.5.2.dist-info/top_level.txt
fkin_anfu-0.5.2.dist-info/RECORD
