Metadata-Version: 2.4
Name: fkin_anfu
Version: 0.5.2
Summary: Network Security Automation Toolkit
Author-email: cyhfvg <public.guangzhou.zhang@outlook.com>
License: Copyright 2025 cyhfvg
Project-URL: Homepage, https://github.com/cyhfvg/fkin_anfu
Requires-Python: >=3.8
License-File: LICENSE
Requires-Dist: pandas
Requires-Dist: sqlalchemy
Requires-Dist: pymysql
Requires-Dist: openpyxl
Requires-Dist: XlsxWriter
Requires-Dist: python-dotenv
Requires-Dist: colorama
Requires-Dist: pydantic
Requires-Dist: pyfiglet
Provides-Extra: dev
Requires-Dist: pytest; extra == "dev"
Requires-Dist: flake8; extra == "dev"
Requires-Dist: black; extra == "dev"
Requires-Dist: isort; extra == "dev"
Dynamic: license-file
